giquant/trade/__init__.py
giquant/trade/borsdata.py
giquant/trade/cc.py
giquant/trade/cf.py
giquant/trade/cl.py
giquant/trade/contracts.yaml
giquant/trade/cot.py
giquant/trade/dwnl.py
giquant/trade/finra.py
giquant/trade/mywrds.py
giquant/trade/screen.py
giquant/trade/yf.py
giquant/tsl/__init__.py
giquant/tsl/create.py
giquant/tsl/expr.py
giquant/tsl/gg.py
giquant/tsl/helpers.py
giquant/tsl/index.py
giquant/tsl/merge.py
giquant/tsl/passenger_wsgi.py
giquant/tsl/pr.py
giquant/tsl/run.py
giquant/tsl/server.py
giquant/tsl/sql.py
giquant/tsl/tools.py
giquant/tsl/server_modules/expr_form.py
giquant/tsl/server_modules/gg_form.py
giquant/tsl/server_modules/index.py
giquant/tsl/server_modules/pr_form.py
giquant/tsl/server_modules/run_form.py
giquant/tsl/server_modules/sql_form.py
giquant/tsl/server_modules/templates/db.html
giquant/tsl/server_modules/templates/expr_form.html
giquant/tsl/server_modules/templates/gg_form.html
giquant/tsl/server_modules/templates/index.html
giquant/tsl/server_modules/templates/main.html
giquant/tsl/server_modules/templates/pr_form.html
giquant/tsl/server_modules/templates/run_form.html
giquant/tsl/server_modules/templates/sql_form.html
giquant-2025.0.7.dist-info/licenses/LICENSE
giquant-2025.0.7.dist-info/METADATA
giquant-2025.0.7.dist-info/WHEEL
giquant-2025.0.7.dist-info/top_level.txt
giquant-2025.0.7.dist-info/RECORD
