Metadata-Version: 2.4
Name: giquant
Version: 2025.0.7
Summary: Quant & Trading tools.
Author: GiQuant
Author-email: quant@gizur.com
Maintainer-email: GiQuant <quant@gizur.com>
License: ISC License 
Project-URL: Repository, https://github.com/giquant/giquant.git
Keywords: quant,quantative finance,trading,Commitment Of Traders Report
Classifier: Development Status :: 4 - Beta
Classifier: Programming Language :: Python
Requires-Python: >=3.8.5
License-File: LICENSE
Requires-Dist: requests
Requires-Dist: wget
Requires-Dist: pandas
Requires-Dist: numpy
Requires-Dist: duckdb
Requires-Dist: duckdb_engine
Requires-Dist: pyarrow
Requires-Dist: fastparquet
Requires-Dist: pyyaml
Requires-Dist: lark
Requires-Dist: pyreadr
Requires-Dist: py_vollib
Requires-Dist: scikit-learn
Requires-Dist: ansi2html
Requires-Dist: seaborn
Requires-Dist: pandas_ods_reader
Requires-Dist: SQLAlchemy
Requires-Dist: tabulate
Dynamic: license-file
